{
  "metadata": {
    "url": "https://blog.cloudflare.com",
    "navigation_success": true,
    "performance": {
      "loadTime": 1924,
      "domContentLoaded": 914,
      "firstPaint": 844
    },
    "total_resources": 125,
    "timestamp": "2025-04-08 22:09:12"
  },
  "images": [
    {
      "url": "https://cf-assets.www.cloudflare.com/zkvhlag99gkb/69RwBidpiEHCDZ9rFVVk7T/092507edbed698420b89658e5a6d5105/CF_logo_stacked_blktype.png",
      "resource_type": "image",
      "method": "GET",
      "size": 6334,
      "status": 200,
      "content_type": "image/webp",
      "cache_control": "max-age=604800",
      "cdn": "Cloudflare",
      "supports_http3": true,
      "etag": "\"c26d9194cac94ccede244b624d52ae46\"",
      "last_modified": "Thu, 10 Oct 2024 04:25:34 GMT",
      "expires": "",
      "age": "454527",
      "server": "cloudflare"
    },
    {
      "url": "https://blog.cloudflare.com/images/magnifier.svg",
      "resource_type": "image",
      "method": "GET",
      "size": 526,
      "status": 200,
      "content_type": "image/svg+xml",
      "cache_control": "public, max-age=1200",
      "cdn": "Cloudflare",
      "supports_http3": true,
      "etag": "W/\"130e649cb43e040e7e848d69a424f060\"",
      "last_modified": "",
      "expires": "Tue, 08 Apr 2025 22:28:54 GMT",
      "age": "4221",
      "server": "cloudflare"
    },
    {
      "url": "https://blog.cloudflare.com/images/hamburger.svg",
      "resource_type": "image",
      "method": "GET",
      "size": 309,
      "status": 200,
      "content_type": "image/svg+xml",
      "cache_control": "public, max-age=1200",
      "cdn": "Cloudflare",
      "supports_http3": true,
      "etag": "W/\"56565972cd83a7f61f02617f05d5ea39\"",
      "last_modified": "",
      "expires": "Tue, 08 Apr 2025 22:28:54 GMT",
      "age": "",
      "server": "cloudflare"
    },
    {
      "url": "https://blog.cloudflare.com/cdn-cgi/image/format=auto,dpr=3,width=64,height=64,gravity=face,fit=crop,zoom=0.5/https://cf-assets.www.cloudflare.com/zkvhlag99gkb/5cfasTtVaoOsISarcB9F4Z/1686863c1bbd4dc0b74c7229cfcee42c/Korinne_Alpers.jpg",
      "resource_type": "image",
      "method": "GET",
      "size": 4235,
      "status": 200,
      "content_type": "image/avif",
      "cache_control": "max-age=604800",
      "cdn": "Cloudflare",
      "supports_http3": true,
      "etag": "\"cft8JFVtHzlj3p28nnRXF7mlQpoWUsopIvKVkBu1I2DQ:66008259e453d1f5583b822361d59e44\"",
      "last_modified": "Tue, 08 Apr 2025 00:22:04 GMT",
      "expires": "",
      "age": "",
      "server": "cloudflare"
    },
    {
      "url": "https://cf-assets.www.cloudflare.com/zkvhlag99gkb/4XxYGJI8hHbY3GQWzuM2BA/bfad24f662883f169142de42806316b3/Feature_Image.png",
      "resource_type": "image",
      "method": "GET",
      "size": 91496,
      "status": 200,
      "content_type": "image/webp",
      "cache_control": "max-age=604800",
      "cdn": "Cloudflare",
      "supports_http3": true,
      "etag": "\"2cdab35e4a7bee6cc9de49da2f1f0d2d\"",
      "last_modified": "Tue, 08 Apr 2025 00:17:42 GMT",
      "expires": "",
      "age": "32790",
      "server": "cloudflare"
    },
    {
      "url": "https://blog.cloudflare.com/cdn-cgi/image/format=auto,dpr=3,width=64,height=64,gravity=face,fit=crop,zoom=0.5/https://cf-assets.www.cloudflare.com/zkvhlag99gkb/23kOes6NFYUjdoPUWdaUdq/485828df0ae319f08e6b01c0acc6486e/dario.png",
      "resource_type": "image",
      "method": "GET",
      "size": 2836,
      "status": 200,
      "content_type": "image/avif",
      "cache_control": "max-age=604800",
      "cdn": "Cloudflare",
      "supports_http3": true,
      "etag": "\"cfhn0V6bKBfM4tEofn_9VCwDXLoWUsopIvKVkBu1I2DQ:45c0e798eeea7569ee353524d8a67c1c\"",
      "last_modified": "Thu, 10 Oct 2024 00:36:30 GMT",
      "expires": "",
      "age": "",
      "server": "cloudflare"
    },
    {
      "url": "https://blog.cloudflare.com/cdn-cgi/image/format=auto,dpr=3,width=64,height=64,gravity=face,fit=crop,zoom=0.5/https://cf-assets.www.cloudflare.com/zkvhlag99gkb/s9DHTbRIKnmQ9tRYfkJvc/adbe09b00d39831703ab5b740b3bd372/Victor_Berchet.jpg",
      "resource_type": "image",
      "method": "GET",
      "size": 8807,
      "status": 200,
      "content_type": "image/avif",
      "cache_control": "max-age=604800",
      "cdn": "Cloudflare",
      "supports_http3": true,
      "etag": "\"cff67OE6SlPk3QvmEh9hVseo7KoWUsopIvKVkBu1I2DQ:5ba15fd0bb912c3ccb0ab9de447acc9d\"",
      "last_modified": "Mon, 07 Apr 2025 06:45:45 GMT",
      "expires": "",
      "age": "",
      "server": "cloudflare"
    },
    {
      "url": "https://blog.cloudflare.com/cdn-cgi/image/format=auto,dpr=3,width=64,height=64,gravity=face,fit=crop,zoom=0.5/https://cf-assets.www.cloudflare.com/zkvhlag99gkb/4YgP47iRhXzZUipbOYwuZS/da4f98eec3101072183ed522c96ed7be/IMG_20250326_160125.jpg",
      "resource_type": "image",
      "method": "GET",
      "size": 2436,
      "status": 200,
      "content_type": "image/avif",
      "cache_control": "max-age=604800",
      "cdn": "Cloudflare",
      "supports_http3": true,
      "etag": "\"cfSYIbfEgQbbkZVEvmYi20FpOZoWUsopIvKVkBu1I2DQ:28cc6084099ef38f4f6219cdfce09c4b-2\"",
      "last_modified": "Mon, 07 Apr 2025 06:47:17 GMT",
      "expires": "",
      "age": "",
      "server": "cloudflare"
    },
    {
      "url": "https://blog.cloudflare.com/cdn-cgi/image/format=auto,dpr=3,width=64,height=64,gravity=face,fit=crop,zoom=0.5/https://cf-assets.www.cloudflare.com/zkvhlag99gkb/6VOJd4s366Q3PvzZ74WQ1g/83f99bc26107942fa21d5a77978f6eca/4PPZ5PC.jpeg",
      "resource_type": "image",
      "method": "GET",
      "size": 4591,
      "status": 200,
      "content_type": "image/avif",
      "cache_control": "max-age=604800",
      "cdn": "Cloudflare",
      "supports_http3": true,
      "etag": "\"cfcXlPxy_8OlPorha_LxYlCMyLoWUsopIvKVkBu1I2DQ:7c0013565ccd32e15a76455f0e8467b8\"",
      "last_modified": "Mon, 07 Apr 2025 06:48:41 GMT",
      "expires": "",
      "age": "",
      "server": "cloudflare"
    },
    {
      "url": "https://blog.cloudflare.com/cdn-cgi/image/format=auto,dpr=3,width=64,height=64,gravity=face,fit=crop,zoom=0.5/https://cf-assets.www.cloudflare.com/zkvhlag99gkb/1moTBd0N5e74Bn9NWn2ksO/9642b164dcf16e501a79e56520548aa2/andrew-repp.jpg",
      "resource_type": "image",
      "method": "GET",
      "size": 2863,
      "status": 200,
      "content_type": "image/avif",
      "cache_control": "max-age=604800",
      "cdn": "Cloudflare",
      "supports_http3": true,
      "etag": "\"cfUXwWICuW_RuMVqrbgT7f85RboWUsopIvKVkBu1I2DQ:70e61b5941120c7147090a269d69b267\"",
      "last_modified": "Thu, 10 Oct 2024 01:00:12 GMT",
      "expires": "",
      "age": "",
      "server": "cloudflare"
    },
    {
      "url": "https://blog.cloudflare.com/cdn-cgi/image/format=auto,dpr=3,width=64,height=64,gravity=face,fit=crop,zoom=0.5/https://cf-assets.www.cloudflare.com/zkvhlag99gkb/28IQWzENpxkBKoy5vIJWKu/d961f90b6c3af310b8ca50e6f6dfe51e/matt-alonso.jpg",
      "resource_type": "image",
      "method": "GET",
      "size": 2455,
      "status": 200,
      "content_type": "image/avif",
      "cache_control": "max-age=604800",
      "cdn": "Cloudflare",
      "supports_http3": true,
      "etag": "\"cfqwDPm9FRyFjH4Tw7G2RmJjAWoWUsopIvKVkBu1I2DQ:0b4fcb14cdfebc6f403b744a9292cf43\"",
      "last_modified": "Thu, 10 Oct 2024 02:27:44 GMT",
      "expires": "",
      "age": "",
      "server": "cloudflare"
    },
    {
      "url": "https://blog.cloudflare.com/cdn-cgi/image/format=auto,dpr=3,width=64,height=64,gravity=face,fit=crop,zoom=0.5/https://cf-assets.www.cloudflare.com/zkvhlag99gkb/2niktUqyQO5YzVIBCwrBGl/9474ec9faff3b27f7ec9013a066b9b54/Thomas_Gauvin.jpg",
      "resource_type": "image",
      "method": "GET",
      "size": 3042,
      "status": 200,
      "content_type": "image/avif",
      "cache_control": "max-age=604800",
      "cdn": "Cloudflare",
      "supports_http3": true,
      "etag": "\"cfJayoKErzzEkloNpNR7vz5gf-oWUsopIvKVkBu1I2DQ:6dfb6d095108055ff92ffb98c10a9f97\"",
      "last_modified": "Thu, 10 Oct 2024 01:19:29 GMT",
      "expires": "",
      "age": "",
      "server": "cloudflare"
    },
    {
      "url": "https://blog.cloudflare.com/cdn-cgi/image/format=auto,dpr=3,width=64,height=64,gravity=face,fit=crop,zoom=0.5/https://cf-assets.www.cloudflare.com/zkvhlag99gkb/7moLa3bYyUWGSpTYWzP93F/558f6a70613f5713291231ddd57448cc/Kirk_Nickish.jpg",
      "resource_type": "image",
      "method": "GET",
      "size": 3463,
      "status": 200,
      "content_type": "image/avif",
      "cache_control": "max-age=604800",
      "cdn": "Cloudflare",
      "supports_http3": true,
      "etag": "\"cfKHcp0qoj60Ub_l8tIn3Ke8Q_oWUsopIvKVkBu1I2DQ:e2ccf6f983e9367ff335dfbc2f11d8d9\"",
      "last_modified": "Mon, 07 Apr 2025 04:06:23 GMT",
      "expires": "",
      "age": "",
      "server": "cloudflare"
    },
    {
      "url": "https://blog.cloudflare.com/cdn-cgi/image/format=auto,dpr=3,width=64,height=64,gravity=face,fit=crop,zoom=0.5/https://cf-assets.www.cloudflare.com/zkvhlag99gkb/Nt978ELmW8HwrYwJDdwUz/c463d2ccaa54ed75b9c2e3f0fa0a7385/Yagiz_Nizipli.jpg",
      "resource_type": "image",
      "method": "GET",
      "size": 4109,
      "status": 200,
      "content_type": "image/avif",
      "cache_control": "max-age=604800",
      "cdn": "Cloudflare",
      "supports_http3": true,
      "etag": "\"cfgcbDDRauobHZcu74oRcPCBBDoWUsopIvKVkBu1I2DQ:57cb999c69bcb2ad695714b7f08c8bfa\"",
      "last_modified": "Thu, 20 Mar 2025 08:25:33 GMT",
      "expires": "",
      "age": "",
      "server": "cloudflare"
    },
    {
      "url": "https://blog.cloudflare.com/cdn-cgi/image/format=auto,dpr=3,width=64,height=64,gravity=face,fit=crop,zoom=0.5/https://cf-assets.www.cloudflare.com/zkvhlag99gkb/4LgURMZO1krMjwJzfMDsJa/bfba26fa5e171a19e8b84d02d62b13b9/James_Opstad.jpg",
      "resource_type": "image",
      "method": "GET",
      "size": 4696,
      "status": 200,
      "content_type": "image/avif",
      "cache_control": "max-age=604800",
      "cdn": "Cloudflare",
      "supports_http3": true,
      "etag": "\"cfInaq3_kaGRtfJ4WlDW72P63ZoWUsopIvKVkBu1I2DQ:cce2eda7b861dbf092b5256855f5bb0a\"",
      "last_modified": "Mon, 07 Apr 2025 06:25:36 GMT",
      "expires": "",
      "age": "",
      "server": "cloudflare"
    },
    {
      "url": "https://blog.cloudflare.com/cdn-cgi/image/format=auto,dpr=3,width=64,height=64,gravity=face,fit=crop,zoom=0.5/https://cf-assets.www.cloudflare.com/zkvhlag99gkb/2p5W3FQx293vHg4DXN0ND5/35db5a05651ed668ba87fee024208104/peter-bacon-darwin.png",
      "resource_type": "image",
      "method": "GET",
      "size": 4952,
      "status": 200,
      "content_type": "image/avif",
      "cache_control": "max-age=604800",
      "cdn": "Cloudflare",
      "supports_http3": true,
      "etag": "\"cfvBhX3Pj1HTGf-uF9FzKhQ7XIoWUsopIvKVkBu1I2DQ:e46d13b0a882f47dab0f3d2be18cc586\"",
      "last_modified": "Thu, 10 Oct 2024 00:36:47 GMT",
      "expires": "",
      "age": "",
      "server": "cloudflare"
    },
    {
      "url": "https://blog.cloudflare.com/cdn-cgi/image/format=auto,dpr=3,width=64,height=64,gravity=face,fit=crop,zoom=0.5/https://cf-assets.www.cloudflare.com/zkvhlag99gkb/4bFcaTr1FpTJBKV7y849pd/499e62c642e20b9c8e83c9ce94f16728/igor.jpeg",
      "resource_type": "image",
      "method": "GET",
      "size": 3283,
      "status": 200,
      "content_type": "image/avif",
      "cache_control": "max-age=604800",
      "cdn": "Cloudflare",
      "supports_http3": true,
      "etag": "\"cfBMFtCHocFvnZ8EQbZmIFSBgjoWUsopIvKVkBu1I2DQ:9bd84cd1e45b54e609a9598af1ba4073\"",
      "last_modified": "Thu, 10 Oct 2024 00:36:43 GMT",
      "expires": "",
      "age": "",
      "server": "cloudflare"
    },
    {
      "url": "https://blog.cloudflare.com/cdn-cgi/image/format=auto,dpr=3,width=64,height=64,gravity=face,fit=crop,zoom=0.5/https://cf-assets.www.cloudflare.com/zkvhlag99gkb/2WVp9J8BoRJaBMR7crkqWH/f7814ed0df05b50babb47c6ff5b936e5/nevi.png",
      "resource_type": "image",
      "method": "GET",
      "size": 4556,
      "status": 200,
      "content_type": "image/avif",
      "cache_control": "max-age=604800",
      "cdn": "Cloudflare",
      "supports_http3": true,
      "etag": "\"cfd_XmaG1LVE-XefMEcKqe6uNxoWUsopIvKVkBu1I2DQ:6a9635ddb82dd76e4f4b5bf1a2764692\"",
      "last_modified": "Thu, 10 Oct 2024 00:34:43 GMT",
      "expires": "",
      "age": "",
      "server": "cloudflare"
    },
    {
      "url": "https://blog.cloudflare.com/cdn-cgi/image/format=auto,dpr=3,width=64,height=64,gravity=face,fit=crop,zoom=0.5/https://cf-assets.www.cloudflare.com/zkvhlag99gkb/3viCDHdRdgbirjk7W1OqS5/10437b1d8ddeadc34fee3796dbfefa7e/Brandon_Strittmatter.webp",
      "resource_type": "image",
      "method": "GET",
      "size": 4350,
      "status": 200,
      "content_type": "image/avif",
      "cache_control": "max-age=604800",
      "cdn": "Cloudflare",
      "supports_http3": true,
      "etag": "\"cf-XyYDwIy_zvLo31VtF2v-v3BoWUsopIvKVkBu1I2DQ:99abf44965097bd703fab9387c4cfaa5\"",
      "last_modified": "Sat, 05 Apr 2025 21:24:54 GMT",
      "expires": "",
      "age": "",
      "server": "cloudflare"
    },
    {
      "url": "https://blog.cloudflare.com/cdn-cgi/image/format=auto,dpr=3,width=64,height=64,gravity=face,fit=crop,zoom=0.5/https://cf-assets.www.cloudflare.com/zkvhlag99gkb/7xP5qePZD9eyVtwIesXYxh/e714aaa573161ec9eb48d59bd1aa6225/silverlock.jpeg",
      "resource_type": "image",
      "method": "GET",
      "size": 5174,
      "status": 200,
      "content_type": "image/avif",
      "cache_control": "max-age=604800",
      "cdn": "Cloudflare",
      "supports_http3": true,
      "etag": "\"cfipXH8ufXAyJRRWbo4QDyyUecoWUsopIvKVkBu1I2DQ:7a550c5366ad94bca4c5abc8ec978cc0\"",
      "last_modified": "Thu, 10 Oct 2024 00:32:37 GMT",
      "expires": "",
      "age": "",
      "server": "cloudflare"
    },
    {
      "url": "https://blog.cloudflare.com/cdn-cgi/image/format=auto,dpr=3,width=64,height=64,gravity=face,fit=crop,zoom=0.5/https://cf-assets.www.cloudflare.com/zkvhlag99gkb/66pIfBfhDUadwWztfEDfXe/66d41b9c01e48856fd1deb323d9007a9/sid.jpg",
      "resource_type": "image",
      "method": "GET",
      "size": 6440,
      "status": 200,
      "content_type": "image/avif",
      "cache_control": "max-age=604800",
      "cdn": "Cloudflare",
      "supports_http3": true,
      "etag": "\"cf6f7BTsALVezzFRFDd6kIlIamoWUsopIvKVkBu1I2DQ:0a5069f18d53c47107268de831cfa184\"",
      "last_modified": "Thu, 10 Oct 2024 01:44:47 GMT",
      "expires": "",
      "age": "",
      "server": "cloudflare"
    },
    {
      "url": "https://blog.cloudflare.com/cdn-cgi/image/format=auto,dpr=3,width=64,height=64,gravity=face,fit=crop,zoom=0.5/https://cf-assets.www.cloudflare.com/zkvhlag99gkb/3RnKI54hxLOIRs0QBSZgxa/e71b8f7a5ccadb45dd553c69f8ffe539/anni.png",
      "resource_type": "image",
      "method": "GET",
      "size": 5343,
      "status": 200,
      "content_type": "image/avif",
      "cache_control": "max-age=604800",
      "cdn": "Cloudflare",
      "supports_http3": true,
      "etag": "\"cfUtxU-lnQS2VyQjUzV3ymMK_4oWUsopIvKVkBu1I2DQ:3051923f574097ed439ec2bd9ead5e92\"",
      "last_modified": "Thu, 10 Oct 2024 01:45:05 GMT",
      "expires": "",
      "age": "",
      "server": "cloudflare"
    },
    {
      "url": "https://blog.cloudflare.com/cdn-cgi/image/format=auto,dpr=3,width=64,height=64,gravity=face,fit=crop,zoom=0.5/https://cf-assets.www.cloudflare.com/zkvhlag99gkb/56u5zfWi9255rUocOgksl0/5eb2eb16e26893d259f7b00af85e8417/rita.png",
      "resource_type": "image",
      "method": "GET",
      "size": 5960,
      "status": 200,
      "content_type": "image/avif",
      "cache_control": "max-age=604800",
      "cdn": "Cloudflare",
      "supports_http3": true,
      "etag": "\"cfQkfTBYcf3VHWQMW7WiJrLXvooWUsopIvKVkBu1I2DQ:09c6b66def59d1b0895996434344beaf\"",
      "last_modified": "Thu, 10 Oct 2024 00:37:50 GMT",
      "expires": "",
      "age": "",
      "server": "cloudflare"
    },
    {
      "url": "https://blog.cloudflare.com/cdn-cgi/image/format=auto,dpr=3,width=64,height=64,gravity=face,fit=crop,zoom=0.5/https://cf-assets.www.cloudflare.com/zkvhlag99gkb/bY78cK0burCjZbD6jOgAH/a8479b5ea6dd8fb3acb41227c1a4ad0e/dina.jpg",
      "resource_type": "image",
      "method": "GET",
      "size": 4897,
      "status": 200,
      "content_type": "image/avif",
      "cache_control": "max-age=604800",
      "cdn": "Cloudflare",
      "supports_http3": true,
      "etag": "\"cfjj45oblksCqKmNoRIr0vXiHDoWUsopIvKVkBu1I2DQ:22e97e0a4440f47e3bf1df7910e0aa42\"",
      "last_modified": "Thu, 10 Oct 2024 01:11:39 GMT",
      "expires": "",
      "age": "",
      "server": "cloudflare"
    },
    {
      "url": "https://blog.cloudflare.com/cdn-cgi/image/format=auto,dpr=3,width=64,height=64,gravity=face,fit=crop,zoom=0.5/https://cf-assets.www.cloudflare.com/zkvhlag99gkb/47vp9vXZx8EXsnBFmCK8NS/2f7f46cdadaa4545e2b61d9c674d1e5a/vy.png",
      "resource_type": "image",
      "method": "GET",
      "size": 3567,
      "status": 200,
      "content_type": "image/avif",
      "cache_control": "max-age=604800",
      "cdn": "Cloudflare",
      "supports_http3": true,
      "etag": "\"cf4yzxoxhs4D_uNIcIucGad-eeoWUsopIvKVkBu1I2DQ:3e96fa81a0d53448784bb520c488ff9b\"",
      "last_modified": "Thu, 10 Oct 2024 00:31:17 GMT",
      "expires": "",
      "age": "",
      "server": "cloudflare"
    },
    {
      "url": "https://blog.cloudflare.com/cdn-cgi/image/format=auto,dpr=3,width=64,height=64,gravity=face,fit=crop,zoom=0.5/https://cf-assets.www.cloudflare.com/zkvhlag99gkb/1hrcl3aVtUbBuCMeuXETWy/93dbfbc7d41c09ba35d863312dbde89d/michelle.jpg",
      "resource_type": "image",
      "method": "GET",
      "size": 2017,
      "status": 200,
      "content_type": "image/avif",
      "cache_control": "max-age=604800",
      "cdn": "Cloudflare",
      "supports_http3": true,
      "etag": "\"cfKA4w3M_2fV1XtRnI6zB9h67joWUsopIvKVkBu1I2DQ:0b452cd2b34e3a77419e63c416e7b2d8\"",
      "last_modified": "Thu, 10 Oct 2024 01:10:55 GMT",
      "expires": "",
      "age": "",
      "server": "cloudflare"
    },
    {
      "url": "https://blog.cloudflare.com/cdn-cgi/image/format=auto,dpr=3,width=64,height=64,gravity=face,fit=crop,zoom=0.5/https://cf-assets.www.cloudflare.com/zkvhlag99gkb/8yRqemLc8lLhE9Uwzd7G4/a303cca84c1840cc961831f1ea6b4213/jesse.jpg",
      "resource_type": "image",
      "method": "GET",
      "size": 4128,
      "status": 200,
      "content_type": "image/avif",
      "cache_control": "max-age=604800",
      "cdn": "Cloudflare",
      "supports_http3": true,
      "etag": "\"cfFDdwhtkGFYjq1jjXFArkE1wkoWUsopIvKVkBu1I2DQ:38977f0546d8f09565fb10019c3253cb\"",
      "last_modified": "Thu, 10 Oct 2024 00:31:35 GMT",
      "expires": "",
      "age": "",
      "server": "cloudflare"
    },
    {
      "url": "https://blog.cloudflare.com/cdn-cgi/image/format=auto,dpr=3,width=64,height=64,gravity=face,fit=crop,zoom=0.5/https://cf-assets.www.cloudflare.com/zkvhlag99gkb/7KZ3JdO5ODe3FLdN8ng1Nc/0dbaf23c66ad71fd5b338587ce057ae2/nikhil.jpeg",
      "resource_type": "image",
      "method": "GET",
      "size": 5144,
      "status": 200,
      "content_type": "image/avif",
      "cache_control": "max-age=604800",
      "cdn": "Cloudflare",
      "supports_http3": true,
      "etag": "\"cf-xqZ6g8gWH4mu0KYEHhtYKdIoWUsopIvKVkBu1I2DQ:5ec295f8891d9290b285c8cdfa4275bc\"",
      "last_modified": "Thu, 10 Oct 2024 01:10:36 GMT",
      "expires": "",
      "age": "",
      "server": "cloudflare"
    },
    {
      "url": "https://blog.cloudflare.com/cdn-cgi/image/format=auto,dpr=3,width=64,height=64,gravity=face,fit=crop,zoom=0.5/https://cf-assets.www.cloudflare.com/zkvhlag99gkb/2bYajiPZgZWmNEFDQV3vDd/1d5c62f0be1db81863ef47dffd462ae7/xlarge.png",
      "resource_type": "image",
      "method": "GET",
      "size": 5024,
      "status": 200,
      "content_type": "image/avif",
      "cache_control": "max-age=604800",
      "cdn": "Cloudflare",
      "supports_http3": true,
      "etag": "\"cf9oun0UCL0-UAxnfdGs1EIGI9oWUsopIvKVkBu1I2DQ:1bd82aa4e5fc7beae81b1078440483ef\"",
      "last_modified": "Fri, 04 Apr 2025 00:30:06 GMT",
      "expires": "",
      "age": "",
      "server": "cloudflare"
    },
    {
      "url": "https://blog.cloudflare.com/cdn-cgi/image/format=auto,dpr=3,width=64,height=64,gravity=face,fit=crop,zoom=0.5/https://cf-assets.www.cloudflare.com/zkvhlag99gkb/5eGiJ4EopefC4KhjH4khYQ/526640356ab514827ac816ee0708edbb/deanna.jpg",
      "resource_type": "image",
      "method": "GET",
      "size": 4083,
      "status": 200,
      "content_type": "image/avif",
      "cache_control": "max-age=604800",
      "cdn": "Cloudflare",
      "supports_http3": true,
      "etag": "\"cfdyL6ptY5oB98IKNIVsqj3zs3oWUsopIvKVkBu1I2DQ:e13dac60964c8afb2832e19a933a7d6d\"",
      "last_modified": "Thu, 10 Oct 2024 00:35:09 GMT",
      "expires": "",
      "age": "",
      "server": "cloudflare"
    },
    {
      "url": "https://blog.cloudflare.com/cdn-cgi/image/format=auto,dpr=3,width=64,height=64,gravity=face,fit=crop,zoom=0.5/https://cf-assets.www.cloudflare.com/zkvhlag99gkb/5r9TW9rIM9lAdg4oaG58C1/01da6147aa0cb6a887010588332800f0/Nick_Skehin.webp",
      "resource_type": "image",
      "method": "GET",
      "size": 5041,
      "status": 200,
      "content_type": "image/avif",
      "cache_control": "max-age=604800",
      "cdn": "Cloudflare",
      "supports_http3": true,
      "etag": "\"cfKexzDvypZncDKi0_2_z-OUHvoWUsopIvKVkBu1I2DQ:5c8f5b2eefbd5dea1293e460fa748111\"",
      "last_modified": "Thu, 03 Apr 2025 09:27:42 GMT",
      "expires": "",
      "age": "",
      "server": "cloudflare"
    },
    {
      "url": "https://blog.cloudflare.com/cdn-cgi/image/format=auto,dpr=3,width=64,height=64,gravity=face,fit=crop,zoom=0.5/https://cf-assets.www.cloudflare.com/zkvhlag99gkb/658l52gIu4kyDjwnJCelUt/d0a7c86def68692d50d9b4a0d6fc2f18/_tmp_mini_magick20221116-43-2dcplr.jpg",
      "resource_type": "image",
      "method": "GET",
      "size": 3901,
      "status": 200,
      "content_type": "image/avif",
      "cache_control": "max-age=604800",
      "cdn": "Cloudflare",
      "supports_http3": true,
      "etag": "\"cfNoa_Rch54YffY26etfXWmdDIoWUsopIvKVkBu1I2DQ:ff5a8bad64170038ac232f195cdcdcb1\"",
      "last_modified": "Fri, 28 Mar 2025 18:07:30 GMT",
      "expires": "",
      "age": "",
      "server": "cloudflare"
    },
    {
      "url": "https://blog.cloudflare.com/cdn-cgi/image/format=auto,dpr=3,width=64,height=64,gravity=face,fit=crop,zoom=0.5/https://cf-assets.www.cloudflare.com/zkvhlag99gkb/1e9gtWsffhoAWG0rTN45cR/35204e3d77d1a90feeb57a32e388daca/alex.jpg",
      "resource_type": "image",
      "method": "GET",
      "size": 4837,
      "status": 200,
      "content_type": "image/avif",
      "cache_control": "max-age=604800",
      "cdn": "Cloudflare",
      "supports_http3": true,
      "etag": "\"cfxD2tOpDiOJvG5E19A81rsJ4WoWUsopIvKVkBu1I2DQ:767352c93c132f92696e03bed7a919bf\"",
      "last_modified": "Thu, 10 Oct 2024 05:49:45 GMT",
      "expires": "",
      "age": "",
      "server": "cloudflare"
    },
    {
      "url": "https://blog.cloudflare.com/cdn-cgi/image/format=auto,dpr=3,width=64,height=64,gravity=face,fit=crop,zoom=0.5/https://cf-assets.www.cloudflare.com/zkvhlag99gkb/7ChQBYRPNIiEuQnGQdajbt/3b67f09fd6dae792eb8a1ffafaa1254a/_tmp_mini_magick20221017-43-y5gfah.jpg",
      "resource_type": "image",
      "method": "GET",
      "size": 3387,
      "status": 200,
      "content_type": "image/avif",
      "cache_control": "max-age=604800",
      "cdn": "Cloudflare",
      "supports_http3": true,
      "etag": "\"cfPBlAyI0e_SWwtZvIeiFlLzL5oWUsopIvKVkBu1I2DQ:33f4633631ed37dc5fef92db7240a902\"",
      "last_modified": "Thu, 10 Oct 2024 01:26:29 GMT",
      "expires": "",
      "age": "",
      "server": "cloudflare"
    },
    {
      "url": "https://blog.cloudflare.com/cdn-cgi/image/format=auto,dpr=3,width=64,height=64,gravity=face,fit=crop,zoom=0.5/https://cf-assets.www.cloudflare.com/zkvhlag99gkb/3Ber7SvflfzvyO5J611w7l/59f62d05e428afdd88b10a82857527c0/zaidoon.png",
      "resource_type": "image",
      "method": "GET",
      "size": 3144,
      "status": 200,
      "content_type": "image/avif",
      "cache_control": "max-age=604800",
      "cdn": "Cloudflare",
      "supports_http3": true,
      "etag": "\"cfjyKTD6Y6XElTBX9x4kXgok5koWUsopIvKVkBu1I2DQ:9216b00f6ff643219450231b90b199d7\"",
      "last_modified": "Wed, 09 Oct 2024 21:21:14 GMT",
      "expires": "",
      "age": "",
      "server": "cloudflare"
    },
    {
      "url": "https://blog.cloudflare.com/cdn-cgi/image/format=auto,dpr=3,width=64,height=64,gravity=face,fit=crop,zoom=0.5/https://cf-assets.www.cloudflare.com/zkvhlag99gkb/5vGNsXzZrtSLn2X30pnpUY/6f350e7dd36058a6422f9199b452bb02/john-graham-cumming.jpg",
      "resource_type": "image",
      "method": "GET",
      "size": 3320,
      "status": 200,
      "content_type": "image/avif",
      "cache_control": "max-age=604800",
      "cdn": "Cloudflare",
      "supports_http3": true,
      "etag": "\"cfHyceI3o0IvQrpMjWq2tNr4QtoWUsopIvKVkBu1I2DQ:35ff9ef57f87e3dd495e9c40d12c65ce\"",
      "last_modified": "Thu, 10 Oct 2024 00:59:34 GMT",
      "expires": "",
      "age": "",
      "server": "cloudflare"
    },
    {
      "url": "https://blog.cloudflare.com/cdn-cgi/image/format=auto,dpr=3,width=64,height=64,gravity=face,fit=crop,zoom=0.5/https://cf-assets.www.cloudflare.com/zkvhlag99gkb/17QysF3xmCRN3TqYfLA3xV/5597a6ef339bddc1509da3191bd878c3/emily-terrell.JPG",
      "resource_type": "image",
      "method": "GET",
      "size": 7935,
      "status": 200,
      "content_type": "image/avif",
      "cache_control": "max-age=604800",
      "cdn": "Cloudflare",
      "supports_http3": true,
      "etag": "\"cfpSXneFPlt0t39cRm_XuLsf2zoWUsopIvKVkBu1I2DQ:d273f2db343ce62fb2d1fa4e7c025a8c\"",
      "last_modified": "Wed, 09 Oct 2024 22:48:26 GMT",
      "expires": "",
      "age": "",
      "server": "cloudflare"
    },
    {
      "url": "https://blog.cloudflare.com/cdn-cgi/image/format=auto,dpr=3,width=64,height=64,gravity=face,fit=crop,zoom=0.5/https://cf-assets.www.cloudflare.com/zkvhlag99gkb/4ExrS8aXYNcSJGkDLOTiJX/e581ffcbbc7e7389937f7c35e40014b2/unnamed.webp",
      "resource_type": "image",
      "method": "GET",
      "size": 2110,
      "status": 200,
      "content_type": "image/avif",
      "cache_control": "max-age=604800",
      "cdn": "Cloudflare",
      "supports_http3": true,
      "etag": "\"cfP3IqPPtoLUKWDkfF4817UJjUoWUsopIvKVkBu1I2DQ:572210ae4ba96c45139c02631c2d3f0f\"",
      "last_modified": "Tue, 25 Mar 2025 02:31:12 GMT",
      "expires": "",
      "age": "",
      "server": "cloudflare"
    },
    {
      "url": "https://blog.cloudflare.com/cdn-cgi/image/format=auto,dpr=3,width=64,height=64,gravity=face,fit=crop,zoom=0.5/https://cf-assets.www.cloudflare.com/zkvhlag99gkb/lTJBFKfbqthKbJKPvulre/e8bf53afa7caf1dffeeb55a8c6884959/brendan-irvine-broque.JPG",
      "resource_type": "image",
      "method": "GET",
      "size": 3671,
      "status": 200,
      "content_type": "image/avif",
      "cache_control": "max-age=604800",
      "cdn": "Cloudflare",
      "supports_http3": true,
      "etag": "\"cfzV0OE3kE7qqKdKhtVdKSJpfMoWUsopIvKVkBu1I2DQ:9066fdaea0070857752d588bf888c41e\"",
      "last_modified": "Thu, 10 Oct 2024 00:31:13 GMT",
      "expires": "",
      "age": "",
      "server": "cloudflare"
    },
    {
      "url": "https://blog.cloudflare.com/cdn-cgi/image/format=auto,dpr=3,width=64,height=64,gravity=face,fit=crop,zoom=0.5/https://cf-assets.www.cloudflare.com/zkvhlag99gkb/7dtWmquDOA3nc27l0f7RwQ/43791027b587018e9003bf83e28b77df/glen.jpg",
      "resource_type": "image",
      "method": "GET",
      "size": 5079,
      "status": 200,
      "content_type": "image/avif",
      "cache_control": "max-age=604800",
      "cdn": "Cloudflare",
      "supports_http3": true,
      "etag": "\"cfPKROLvIUJeYQWuCnGPw2Beu3oWUsopIvKVkBu1I2DQ:2dc9659dc6d38f5060b51b0db3a94119\"",
      "last_modified": "Wed, 09 Oct 2024 21:06:55 GMT",
      "expires": "",
      "age": "",
      "server": "cloudflare"
    },
    {
      "url": "https://blog.cloudflare.com/cdn-cgi/image/format=auto,dpr=3,width=64,height=64,gravity=face,fit=crop,zoom=0.5/https://cf-assets.www.cloudflare.com/zkvhlag99gkb/4O71DnT2dvNJsTmWv6PnQI/42a821c809de522be30aa15ea8477fc0/Ethan_Heilman.webp",
      "resource_type": "image",
      "method": "GET",
      "size": 1578,
      "status": 200,
      "content_type": "image/avif",
      "cache_control": "max-age=604800",
      "cdn": "Cloudflare",
      "supports_http3": true,
      "etag": "\"cfufZSBtJYZICWiAk9Ryxj9DSsoWUsopIvKVkBu1I2DQ:5d65c78e0268426737a992e1a0a7702c\"",
      "last_modified": "Mon, 24 Mar 2025 17:36:06 GMT",
      "expires": "",
      "age": "",
      "server": "cloudflare"
    },
    {
      "url": "https://www.cloudflare.com/img/footer/facebook.svg",
      "resource_type": "image",
      "method": "GET",
      "size": 412,
      "status": 200,
      "content_type": "image/svg+xml",
      "cache_control": "",
      "cdn": "Cloudflare",
      "supports_http3": true,
      "etag": "W/\"3125e1ed71d31224dd5ed63d556f79ea\"",
      "last_modified": "",
      "expires": "",
      "age": "",
      "server": "cloudflare"
    },
    {
      "url": "https://www.cloudflare.com/img/footer/twitter.svg",
      "resource_type": "image",
      "method": "GET",
      "size": 680,
      "status": 200,
      "content_type": "image/svg+xml",
      "cache_control": "",
      "cdn": "Cloudflare",
      "supports_http3": true,
      "etag": "W/\"db763538615609c829e7fb895ca01f3e\"",
      "last_modified": "",
      "expires": "",
      "age": "",
      "server": "cloudflare"
    },
    {
      "url": "https://www.cloudflare.com/img/footer/linkedin.svg",
      "resource_type": "image",
      "method": "GET",
      "size": 490,
      "status": 200,
      "content_type": "image/svg+xml",
      "cache_control": "",
      "cdn": "Cloudflare",
      "supports_http3": true,
      "etag": "W/\"2c0975b08e676aae98814a5e2ffdf71f\"",
      "last_modified": "",
      "expires": "",
      "age": "",
      "server": "cloudflare"
    },
    {
      "url": "https://www.cloudflare.com/img/footer/youtube.svg",
      "resource_type": "image",
      "method": "GET",
      "size": 552,
      "status": 200,
      "content_type": "image/svg+xml",
      "cache_control": "",
      "cdn": "Cloudflare",
      "supports_http3": true,
      "etag": "W/\"75df08c7106c437f165ee6d0bdb015ed\"",
      "last_modified": "",
      "expires": "",
      "age": "",
      "server": "cloudflare"
    },
    {
      "url": "https://www.cloudflare.com/img/footer/instagram.svg",
      "resource_type": "image",
      "method": "GET",
      "size": 1425,
      "status": 200,
      "content_type": "image/svg+xml",
      "cache_control": "",
      "cdn": "Cloudflare",
      "supports_http3": true,
      "etag": "W/\"15c1df5c271a1d4f231f3f618ba25330\"",
      "last_modified": "",
      "expires": "",
      "age": "",
      "server": "cloudflare"
    },
    {
      "url": "https://blog.cloudflare.com/images/privacy-options.svg",
      "resource_type": "image",
      "method": "GET",
      "size": 1793,
      "status": 200,
      "content_type": "image/svg+xml",
      "cache_control": "public, max-age=1200",
      "cdn": "Cloudflare",
      "supports_http3": true,
      "etag": "W/\"5a8d3dae7c1ddd64826cea94a93139d4\"",
      "last_modified": "",
      "expires": "Tue, 08 Apr 2025 22:28:54 GMT",
      "age": "",
      "server": "cloudflare"
    },
    {
      "url": "https://blog.cloudflare.com/images/globe-icon.svg",
      "resource_type": "image",
      "method": "GET",
      "size": 1840,
      "status": 200,
      "content_type": "image/svg+xml",
      "cache_control": "public, max-age=1200",
      "cdn": "Cloudflare",
      "supports_http3": true,
      "etag": "W/\"c2c67a36bf16847b1c20b120891d8a11\"",
      "last_modified": "",
      "expires": "Tue, 08 Apr 2025 22:28:54 GMT",
      "age": "",
      "server": "cloudflare"
    },
    {
      "url": "https://px.ads.linkedin.com/collect?v=2&fmt=js&pid=28851&time=1744150134707&li_adsId=639695b5-c9c3-4e46-b00a-519f4e37a076&url=https%3A%2F%2Fblog.cloudflare.com%2F",
      "resource_type": "image",
      "method": "GET",
      "size": 0
    },
    {
      "url": "https://exactly-huge-arachnid.edgecompute.app/?test=bcc6a5c1b80a776e3e00f674e09136aa8b585ed950a086405e56bdf65d02a967&img=1&r=59769834",
      "resource_type": "image",
      "method": "GET",
      "size": 134,
      "status": 200,
      "content_type": "image/svg+xml",
      "cache_control": "no-store",
      "cdn": "Fastly",
      "etag": "",
      "last_modified": "",
      "expires": "",
      "age": "",
      "server": ""
    },
    {
      "url": "https://px.ads.linkedin.com/collect?v=2&fmt=js&pid=28851&time=1744150134707&li_adsId=639695b5-c9c3-4e46-b00a-519f4e37a076&url=https%3A%2F%2Fblog.cloudflare.com%2F&cookiesTest=true",
      "resource_type": "image",
      "method": "GET",
      "size": 0
    },
    {
      "url": "https://d37vlkgj6jn9t1.cloudfront.net/?test=bcc6a5c1b80a776e3e00f674e09136aa8b585ed950a086405e56bdf65d02a967&img=1&r=88547387",
      "resource_type": "image",
      "method": "GET",
      "size": 134,
      "status": 200,
      "content_type": "image/svg+xml",
      "cache_control": "no-store",
      "cdn": "Cloudfront",
      "etag": "",
      "last_modified": "",
      "expires": "",
      "age": "",
      "server": "CloudFront"
    },
    {
      "url": "https://www.linkedin.com/px/li_sync?redirect=https%3A%2F%2Fpx.ads.linkedin.com%2Fcollect%3Fv%3D2%26fmt%3Djs%26pid%3D28851%26time%3D1744150134707%26li_adsId%3D639695b5-c9c3-4e46-b00a-519f4e37a076%26url%3Dhttps%253A%252F%252Fblog.cloudflare.com%252F%26cookiesTest%3Dtrue%26liSync%3Dtrue",
      "resource_type": "image",
      "method": "GET",
      "size": 0
    },
    {
      "url": "https://serverless-benchmarks-js.compute-pipe.com/?test=bcc6a5c1b80a776e3e00f674e09136aa8b585ed950a086405e56bdf65d02a967&img=1&r=57004598",
      "resource_type": "image",
      "method": "GET",
      "size": 134,
      "status": 200,
      "content_type": "image/svg+xml",
      "cache_control": "no-store",
      "cdn": "Cloudflare",
      "etag": "",
      "last_modified": "",
      "expires": "",
      "age": "",
      "server": "cloudflare"
    },
    {
      "url": "https://ad.doubleclick.net/activity;src=9309168;type=a_pag0;cat=3_page;ord=3672008124660;npa=0;auiddc=1685469183.1744150135;u1=page_load;u2=undefined;u3=%2F;u4=en-us;u5=undefined;u6=undefined;u7=undefined;u8=undefined;u9=undefined;u10=undefined;u12=undefined;ps=1;pcor=252796916;uaa=x64;uab=64;uafvl=Chromium%3B134.0.6998.35%7CNot%253AA-Brand%3B24.0.0.0%7CHeadlessChrome%3B134.0.6998.35;uamb=0;uam=;uap=Windows;uapv=10.0;uaw=0;pscdl=noapi;frm=0;_tu=KlA;gtm=45fe5471h1v9164255219z8890325950za201zb891134139;gcs=G111;gcd=13r3r3r3r5l1;dma=0;dc_fmt=5;tag_exp=102509682~102788824~102803279~102813109~102887800~102926062~102975949~103016951~103021830~103027016~103047562~103051953;epver=2?",
      "resource_type": "image",
      "method": "GET",
      "size": 0
    },
    {
      "url": "https://ad.doubleclick.net/activity;register_conversion=1;src=9309168;type=a_pag0;cat=3_page;ord=3672008124660;npa=0;auiddc=1685469183.1744150135;u1=page_load;u2=undefined;u3=%2F;u4=en-us;u5=undefined;u6=undefined;u7=undefined;u8=undefined;u9=undefined;u10=undefined;u12=undefined;ps=1;pcor=252796916;uaa=x64;uab=64;uafvl=Chromium%3B134.0.6998.35%7CNot%253AA-Brand%3B24.0.0.0%7CHeadlessChrome%3B134.0.6998.35;uamb=0;uam=;uap=Windows;uapv=10.0;uaw=0;pscdl=noapi;frm=0;_tu=KlA;gtm=45fe5471h1v9164255219z8890325950za201zb891134139;gcs=G111;gcd=13r3r3r3r5l1;dma=0;dc_fmt=10;tag_exp=102509682~102788824~102803279~102813109~102887800~102926062~102975949~103016951~103021830~103027016~103047562~103051953;epver=2?",
      "resource_type": "image",
      "method": "GET",
      "size": 42,
      "status": 200,
      "content_type": "image/gif",
      "cache_control": "no-cache, must-revalidate",
      "cdn": "Unknown",
      "supports_http3": true,
      "etag": "",
      "last_modified": "",
      "expires": "Fri, 01 Jan 1990 00:00:00 GMT",
      "age": "",
      "server": "cafe"
    },
    {
      "url": "https://px.ads.linkedin.com/collect?v=2&fmt=js&pid=28851&time=1744150134707&li_adsId=639695b5-c9c3-4e46-b00a-519f4e37a076&url=https%3A%2F%2Fblog.cloudflare.com%2F&cookiesTest=true&liSync=true",
      "resource_type": "image",
      "method": "GET",
      "size": 0,
      "status": 200,
      "content_type": "application/javascript",
      "cache_control": "",
      "cdn": "Unknown",
      "etag": "",
      "last_modified": "",
      "expires": "",
      "age": "",
      "server": ""
    },
    {
      "url": "https://ad.doubleclick.net/activity;dc_pre=CKaSgsq5yYwDFWsP0AQdorg5FQ;src=9309168;type=a_pag0;cat=3_page;ord=3672008124660;npa=0;auiddc=1685469183.1744150135;u1=page_load;u2=undefined;u3=%2F;u4=en-us;u5=undefined;u6=undefined;u7=undefined;u8=undefined;u9=undefined;u10=undefined;u12=undefined;ps=1;pcor=252796916;uaa=x64;uab=64;uafvl=Chromium%3B134.0.6998.35%7CNot%253AA-Brand%3B24.0.0.0%7CHeadlessChrome%3B134.0.6998.35;uamb=0;uam=;uap=Windows;uapv=10.0;uaw=0;pscdl=noapi;frm=0;_tu=KlA;gtm=45fe5471h1v9164255219z8890325950za201zb891134139;gcs=G111;gcd=13r3r3r3r5l1;dma=0;dc_fmt=5;tag_exp=102509682~102788824~102803279~102813109~102887800~102926062~102975949~103016951~103021830~103027016~103047562~103051953;epver=2?",
      "resource_type": "image",
      "method": "GET",
      "size": 0
    },
    {
      "url": "https://serverless-benchmarks-rust.compute-pipe.com/?test=bcc6a5c1b80a776e3e00f674e09136aa8b585ed950a086405e56bdf65d02a967&img=1&r=85808833",
      "resource_type": "image",
      "method": "GET",
      "size": 129,
      "status": 200,
      "content_type": "image/svg+xml",
      "cache_control": "no-store",
      "cdn": "Cloudflare",
      "etag": "",
      "last_modified": "",
      "expires": "",
      "age": "",
      "server": "cloudflare"
    },
    {
      "url": "https://adservice.google.com/ddm/fls/z/dc_pre=CKaSgsq5yYwDFWsP0AQdorg5FQ;src=9309168;type=a_pag0;cat=3_page;ord=3672008124660;npa=0;auiddc=*;u1=page_load;u2=undefined;u3=%2F;u4=en-us;u5=undefined;u6=undefined;u7=undefined;u8=undefined;u9=undefined;u10=undefined;u12=undefined;ps=1;pcor=252796916;uaa=x64;uab=64;uafvl=Chromium%3B134.0.6998.35%7CNot%253AA-Brand%3B24.0.0.0%7CHeadlessChrome%3B134.0.6998.35;uamb=0;uam=;uap=Windows;uapv=10.0;uaw=0;pscdl=noapi;frm=0;_tu=KlA;gtm=45fe5471h1v9164255219z8890325950za201zb891134139;gcs=G111;gcd=13r3r3r3r5l1;dma=0;dc_fmt=5;tag_exp=102509682~102788824~102803279~102813109~102887800~102926062~102975949~103016951~103021830~103027016~103047562~103051953;epver=2",
      "resource_type": "image",
      "method": "GET",
      "size": 42,
      "status": 200,
      "content_type": "image/gif",
      "cache_control": "no-cache, must-revalidate",
      "cdn": "Unknown",
      "supports_http3": true,
      "etag": "",
      "last_modified": "",
      "expires": "Fri, 01 Jan 1990 00:00:00 GMT",
      "age": "",
      "server": "cafe"
    },
    {
      "url": "https://uniquely-peaceful-hagfish.edgecompute.app/?test=bcc6a5c1b80a776e3e00f674e09136aa8b585ed950a086405e56bdf65d02a967&img=1&r=71609527",
      "resource_type": "image",
      "method": "GET",
      "size": 129,
      "status": 200,
      "content_type": "image/svg+xml",
      "cache_control": "no-store",
      "cdn": "Fastly",
      "etag": "",
      "last_modified": "",
      "expires": "",
      "age": "",
      "server": ""
    },
    {
      "url": "https://essl-cdxs.edgekey.net/img/r20-100KB.png?r=97538765",
      "resource_type": "image",
      "method": "GET",
      "size": 102400,
      "status": 200,
      "content_type": "image/png",
      "cache_control": "public, max-age=2629743",
      "cdn": "Unknown",
      "etag": "\"63185a62-19000\"",
      "last_modified": "Wed, 07 Sep 2022 08:46:26 GMT",
      "expires": "Fri, 09 May 2025 08:37:58 GMT",
      "age": "",
      "server": "nginx"
    },
    {
      "url": "https://jsdelivr.b-cdn.net/gh/jimaek/testobjects@0.0.1/r20-100KB.png?r=9280829",
      "resource_type": "image",
      "method": "GET",
      "size": 102400,
      "status": 200,
      "content_type": "image/png",
      "cache_control": "public, max-age=31536000, s-maxage=31536000, immutable",
      "cdn": "Fastly",
      "supports_http3": true,
      "etag": "W/\"19000-qSJ5YZCh9buzxBDG7FkVAgUN8E4\"",
      "last_modified": "",
      "expires": "",
      "age": "2089837",
      "server": "BunnyCDN-IL1-1232"
    },
    {
      "url": "https://fastly.jsdelivr.net/gh/jimaek/testobjects@0.0.1/r20-100KB.png?r=80875649",
      "resource_type": "image",
      "method": "GET",
      "size": 102400,
      "status": 200,
      "content_type": "image/png",
      "cache_control": "public, max-age=31536000, s-maxage=31536000, immutable",
      "cdn": "Fastly",
      "supports_http3": true,
      "etag": "W/\"19000-qSJ5YZCh9buzxBDG7FkVAgUN8E4\"",
      "last_modified": "",
      "expires": "",
      "age": "3615813",
      "server": ""
    },
    {
      "url": "https://p36.cedexis-test.com/img/17653/r20-100KB.png?r=63898546",
      "resource_type": "image",
      "method": "GET",
      "size": 102400,
      "status": 200,
      "content_type": "image/png",
      "cache_control": "max-age=2629743, public",
      "cdn": "Unknown",
      "etag": "\"63185a85-19000\"",
      "last_modified": "Wed, 07 Sep 2022 08:47:01 GMT",
      "expires": "",
      "age": "1834789",
      "server": "PWS/8.3.1.0.8"
    },
    {
      "url": "https://testingcf.jsdelivr.net/gh/jimaek/testobjects@0.0.1/r20-100KB.png?r=89471264",
      "resource_type": "image",
      "method": "GET",
      "size": 102400,
      "status": 200,
      "content_type": "image/png",
      "cache_control": "public, max-age=31536000, s-maxage=31536000, immutable",
      "cdn": "Cloudflare",
      "supports_http3": true,
      "etag": "W/\"19000-qSJ5YZCh9buzxBDG7FkVAgUN8E4\"",
      "last_modified": "",
      "expires": "",
      "age": "2026155",
      "server": "cloudflare"
    },
    {
      "url": "https://cedexis-test.akamaized.net/img/r20-100KB.png?r=59568631",
      "resource_type": "image",
      "method": "GET",
      "size": 102400,
      "status": 200,
      "content_type": "image/png",
      "cache_control": "public, max-age=2629743",
      "cdn": "Unknown",
      "etag": "\"63185a62-19000\"",
      "last_modified": "Wed, 07 Sep 2022 08:46:26 GMT",
      "expires": "Fri, 09 May 2025 08:37:59 GMT",
      "age": "",
      "server": "nginx"
    },
    {
      "url": "https://fastly.cedexis-test.com/img/20367/r20-100KB.png?r=2296370",
      "resource_type": "image",
      "method": "GET",
      "size": 102400,
      "status": 200,
      "content_type": "image/png",
      "cache_control": "max-age=2629743, public",
      "cdn": "Fastly",
      "etag": "\"63185a85-19000\"",
      "last_modified": "Wed, 07 Sep 2022 08:47:01 GMT",
      "expires": "",
      "age": "1032513",
      "server": "nginx"
    },
    {
      "url": "https://benchmark.1e100cdn.net/r20-100KB.png?r=82299451",
      "resource_type": "image",
      "method": "GET",
      "size": 102400,
      "status": 200,
      "content_type": "image/png",
      "cache_control": "public,max-age=31536000",
      "cdn": "Unknown",
      "supports_http3": true,
      "etag": "\"5939ad35-19000\"",
      "last_modified": "",
      "expires": "",
      "age": "1966821",
      "server": ""
    },
    {
      "url": "https://ptcfc.com/img/284/r20-100KB.png?r=2716528",
      "resource_type": "image",
      "method": "GET",
      "size": 102400,
      "status": 200,
      "content_type": "image/png",
      "cache_control": "public, max-age=31536000",
      "cdn": "Cloudflare",
      "etag": "\"5668b8ac-19000\"",
      "last_modified": "",
      "expires": "",
      "age": "",
      "server": "cloudflare"
    },
    {
      "url": "https://benchmarks.cdn.compute-pipe.com/r20-100KB.png?r=4690765",
      "resource_type": "image",
      "method": "GET",
      "size": 102400,
      "status": 200,
      "content_type": "image/png",
      "cache_control": "no-store",
      "cdn": "Cloudflare",
      "etag": "",
      "last_modified": "",
      "expires": "",
      "age": "",
      "server": "cloudflare"
    },
    {
      "url": "https://p29.cedexis-test.com/img/r20-100KB.png?r=52145989",
      "resource_type": "image",
      "method": "GET",
      "size": 102400,
      "status": 200,
      "content_type": "image/png",
      "cache_control": "max-age=2629743, public",
      "cdn": "Cloudfront",
      "supports_http3": true,
      "etag": "\"63185a62-19000\"",
      "last_modified": "Wed, 07 Sep 2022 08:46:26 GMT",
      "expires": "",
      "age": "1455199",
      "server": "nginx"
    }
  ],
  "scripts": [
    {
      "url": "https://ot.www.cloudflare.com/public/vendor/onetrust/scripttemplates/otSDKStub.js",
      "resource_type": "script",
      "method": "GET",
      "size": 23567,
      "status": 200,
      "content_type": "application/javascript",
      "cache_control": "public, max-age=0, must-revalidate",
      "cdn": "Cloudflare",
      "supports_http3": true,
      "etag": "W/\"aa857edf236dbed646f3ab3f815d490a\"",
      "last_modified": "",
      "expires": "",
      "age": "",
      "server": "cloudflare"
    },
    {
      "url": "https://blog.cloudflare.com/static/z/i.js",
      "resource_type": "script",
      "method": "GET",
      "size": 2036,
      "status": 200,
      "content_type": "application/javascript",
      "cache_control": "",
      "cdn": "Cloudflare",
      "supports_http3": true,
      "etag": "",
      "last_modified": "",
      "expires": "",
      "age": "",
      "server": "cloudflare"
    },
    {
      "url": "https://static.cloudflareinsights.com/beacon.min.js/vcd15cbe7772f49c399c6a5babf22c1241717689176015",
      "resource_type": "script",
      "method": "GET",
      "size": 19948,
      "status": 200,
      "content_type": "text/javascript;charset=UTF-8",
      "cache_control": "public, max-age=86400",
      "cdn": "Cloudflare",
      "etag": "W/\"2024.6.1\"",
      "last_modified": "Thu, 06 Jun 2024 15:52:56 GMT",
      "expires": "",
      "age": "",
      "server": "cloudflare"
    },
    {
      "url": "https://blog.cloudflare.com/_astro/GoogleAnalytics.DSjxwi8U.js",
      "resource_type": "script",
      "method": "GET",
      "size": 4843,
      "status": 200,
      "content_type": "application/javascript",
      "cache_control": "public, max-age=1200",
      "cdn": "Cloudflare",
      "supports_http3": true,
      "etag": "W/\"73e21c49b2f807d23a58575ae9f16bbe\"",
      "last_modified": "",
      "expires": "Tue, 08 Apr 2025 22:28:54 GMT",
      "age": "4221",
      "server": "cloudflare"
    },
    {
      "url": "https://blog.cloudflare.com/_astro/client.DLO1yDVm.js",
      "resource_type": "script",
      "method": "GET",
      "size": 136099,
      "status": 200,
      "content_type": "application/javascript",
      "cache_control": "public, max-age=1200",
      "cdn": "Cloudflare",
      "supports_http3": true,
      "etag": "W/\"2ebdbc846ea371cfccd6c61d294aebf2\"",
      "last_modified": "",
      "expires": "Tue, 08 Apr 2025 22:28:54 GMT",
      "age": "",
      "server": "cloudflare"
    },
    {
      "url": "https://blog.cloudflare.com/static/z/s.js?z=JTdCJTIyZXhlY3V0ZWQlMjIlM0ElNUIlNUQlMkMlMjJ0JTIyJTNBJTIyVGhlJTIwQ2xvdWRmbGFyZSUyMEJsb2clMjIlMkMlMjJ4JTIyJTNBMC4xMzIyMjk3NzkyMzIwOTUlMkMlMjJ3JTIyJTNBMTI4MCUyQyUyMmglMjIlM0E4MDAlMkMlMjJqJTIyJTNBODAwJTJDJTIyZSUyMiUzQTEyODAlMkMlMjJsJTIyJTNBJTIyaHR0cHMlM0ElMkYlMkZibG9nLmNsb3VkZmxhcmUuY29tJTJGJTIyJTJDJTIyciUyMiUzQSUyMiUyMiUyQyUyMmslMjIlM0EyNCUyQyUyMm4lMjIlM0ElMjJVVEYtOCUyMiUyQyUyMm8lMjIlM0EwJTJDJTIycSUyMiUzQSU1QiU1RCU3RA==",
      "resource_type": "script",
      "method": "GET",
      "size": 10816,
      "status": 200,
      "content_type": "text/javascript; charset=utf-8",
      "cache_control": "",
      "cdn": "Cloudflare",
      "supports_http3": true,
      "etag": "",
      "last_modified": "",
      "expires": "",
      "age": "",
      "server": "cloudflare"
    },
    {
      "url": "https://blog.cloudflare.com/_astro/index.Cmy8rkkD.js",
      "resource_type": "script",
      "method": "GET",
      "size": 698,
      "status": 200,
      "content_type": "application/javascript",
      "cache_control": "public, max-age=1200",
      "cdn": "Cloudflare",
      "supports_http3": true,
      "etag": "W/\"5b5fcb47fdfe5aa567099c46ada73cc2\"",
      "last_modified": "",
      "expires": "Tue, 08 Apr 2025 22:28:54 GMT",
      "age": "",
      "server": "cloudflare"
    },
    {
      "url": "https://blog.cloudflare.com/_astro/ga.DGsU0HSf.js",
      "resource_type": "script",
      "method": "GET",
      "size": 498,
      "status": 200,
      "content_type": "application/javascript",
      "cache_control": "public, max-age=1200",
      "cdn": "Cloudflare",
      "supports_http3": true,
      "etag": "W/\"48df4d29d8ed2cf901c06e00be223006\"",
      "last_modified": "",
      "expires": "Tue, 08 Apr 2025 22:28:54 GMT",
      "age": "4221",
      "server": "cloudflare"
    },
    {
      "url": "https://blog.cloudflare.com/_astro/utils.Bus8dEOG.js",
      "resource_type": "script",
      "method": "GET",
      "size": 1018,
      "status": 200,
      "content_type": "application/javascript",
      "cache_control": "public, max-age=1200",
      "cdn": "Cloudflare",
      "supports_http3": true,
      "etag": "W/\"169e4529ff7ac955558ea87fe7d242b4\"",
      "last_modified": "",
      "expires": "Tue, 08 Apr 2025 22:28:54 GMT",
      "age": "",
      "server": "cloudflare"
    },
    {
      "url": "https://blog.cloudflare.com/_astro/locale.BLlFU-RU.js",
      "resource_type": "script",
      "method": "GET",
      "size": 661,
      "status": 200,
      "content_type": "application/javascript",
      "cache_control": "public, max-age=1200",
      "cdn": "Cloudflare",
      "supports_http3": true,
      "etag": "W/\"6a0d4ee4b6be8a7cc3131fc844659e79\"",
      "last_modified": "",
      "expires": "Tue, 08 Apr 2025 22:28:54 GMT",
      "age": "4221",
      "server": "cloudflare"
    },
    {
      "url": "https://blog.cloudflare.com/_astro/index.Cu3ntQMU.js",
      "resource_type": "script",
      "method": "GET",
      "size": 6783,
      "status": 200,
      "content_type": "application/javascript",
      "cache_control": "public, max-age=1200",
      "cdn": "Cloudflare",
      "supports_http3": true,
      "etag": "W/\"5f20b5d885aa02f51e99145f883df499\"",
      "last_modified": "",
      "expires": "Tue, 08 Apr 2025 22:28:54 GMT",
      "age": "4221",
      "server": "cloudflare"
    },
    {
      "url": "https://blog.cloudflare.com/_astro/Navigation.CSu6dGvY.js",
      "resource_type": "script",
      "method": "GET",
      "size": 8426,
      "status": 200,
      "content_type": "application/javascript",
      "cache_control": "public, max-age=1200",
      "cdn": "Cloudflare",
      "supports_http3": true,
      "etag": "W/\"9782913148988a8ee95c6aa20aeac2ba\"",
      "last_modified": "",
      "expires": "Tue, 08 Apr 2025 22:28:54 GMT",
      "age": "4221",
      "server": "cloudflare"
    },
    {
      "url": "https://www.googletagmanager.com/gtm.js?id=GTM-NDGPDFZ",
      "resource_type": "script",
      "method": "GET",
      "size": 445647,
      "status": 200,
      "content_type": "application/javascript; charset=UTF-8",
      "cache_control": "private, max-age=900",
      "cdn": "Unknown",
      "supports_http3": true,
      "etag": "",
      "last_modified": "Tue, 08 Apr 2025 21:06:31 GMT",
      "expires": "Tue, 08 Apr 2025 22:08:54 GMT",
      "age": "",
      "server": "Google Tag Manager"
    },
    {
      "url": "https://performance.radar.cloudflare.com/beacon.js",
      "resource_type": "script",
      "method": "GET",
      "size": 9837,
      "status": 200,
      "content_type": "text/javascript;charset=UTF-8",
      "cache_control": "no-store, max-age=0",
      "cdn": "Cloudflare",
      "supports_http3": true,
      "etag": "",
      "last_modified": "",
      "expires": "",
      "age": "",
      "server": "cloudflare"
    },
    {
      "url": "https://scout-cdn.salesloft.com/sl.js",
      "resource_type": "script",
      "method": "GET",
      "size": 6105,
      "status": 200,
      "content_type": "application/javascript",
      "cache_control": "public, max-age=14400",
      "cdn": "Cloudflare",
      "supports_http3": true,
      "etag": "W/\"d74cc4825c8e333b2116da3fcc649db1\"",
      "last_modified": "Mon, 13 Dec 2021 16:28:37 GMT",
      "expires": "Wed, 09 Apr 2025 02:08:54 GMT",
      "age": "6960",
      "server": "cloudflare"
    },
    {
      "url": "https://snap.licdn.com/li.lms-analytics/insight.min.js",
      "resource_type": "script",
      "method": "GET",
      "size": 41191,
      "status": 200,
      "content_type": "application/javascript;charset=utf-8",
      "cache_control": "max-age=86400",
      "cdn": "Unknown",
      "supports_http3": true,
      "etag": "",
      "last_modified": "Wed, 22 Jan 2025 19:41:57 GMT",
      "expires": "",
      "age": "",
      "server": ""
    },
    {
      "url": "https://munchkin.marketo.net/munchkin.js",
      "resource_type": "script",
      "method": "GET",
      "size": 1251,
      "status": 200,
      "content_type": "application/x-javascript",
      "cache_control": "",
      "cdn": "Akamai",
      "etag": "\"0c131de2a0d8f1ba69eab7f6866c84dd:1736217492.752819\"",
      "last_modified": "Tue, 07 Jan 2025 02:38:12 GMT",
      "expires": "",
      "age": "",
      "server": "AkamaiNetStorage"
    },
    {
      "url": "https://blog.cloudflare.com/_astro/jsx-runtime.DPFRhYt7.js",
      "resource_type": "script",
      "method": "GET",
      "size": 1002,
      "status": 200,
      "content_type": "application/javascript",
      "cache_control": "public, max-age=1200",
      "cdn": "Cloudflare",
      "supports_http3": true,
      "etag": "W/\"862249fe580012e6d0025a8ca690f234\"",
      "last_modified": "",
      "expires": "Tue, 08 Apr 2025 22:28:54 GMT",
      "age": "",
      "server": "cloudflare"
    },
    {
      "url": "https://blog.cloudflare.com/_astro/navigation.BYP2NKFF.js",
      "resource_type": "script",
      "method": "GET",
      "size": 1250,
      "status": 200,
      "content_type": "application/javascript",
      "cache_control": "public, max-age=1200",
      "cdn": "Cloudflare",
      "supports_http3": true,
      "etag": "W/\"0f43a3286caf48e16245b76bc36fed1a\"",
      "last_modified": "",
      "expires": "Tue, 08 Apr 2025 22:28:54 GMT",
      "age": "4221",
      "server": "cloudflare"
    },
    {
      "url": "https://blog.cloudflare.com/_astro/urls.BpKL7WU2.js",
      "resource_type": "script",
      "method": "GET",
      "size": 544,
      "status": 200,
      "content_type": "application/javascript",
      "cache_control": "public, max-age=1200",
      "cdn": "Cloudflare",
      "supports_http3": true,
      "etag": "W/\"2a6fed774a329407c98d80e8d36276e2\"",
      "last_modified": "",
      "expires": "Tue, 08 Apr 2025 22:28:54 GMT",
      "age": "4221",
      "server": "cloudflare"
    },
    {
      "url": "https://blog.cloudflare.com/_astro/Image.DUg2NaGV.js",
      "resource_type": "script",
      "method": "GET",
      "size": 413,
      "status": 200,
      "content_type": "application/javascript",
      "cache_control": "public, max-age=1200",
      "cdn": "Cloudflare",
      "supports_http3": true,
      "etag": "W/\"1f4d5b7f8873f771d72d5a75df53a75c\"",
      "last_modified": "",
      "expires": "Tue, 08 Apr 2025 22:28:54 GMT",
      "age": "",
      "server": "cloudflare"
    },
    {
      "url": "https://munchkin.marketo.net/164/munchkin.js",
      "resource_type": "script",
      "method": "GET",
      "size": 11374,
      "status": 200,
      "content_type": "application/x-javascript",
      "cache_control": "max-age=8640000",
      "cdn": "Akamai",
      "etag": "\"756f9116836f579d12be8fe786b69d98:1726632111.60799\"",
      "last_modified": "Wed, 18 Sep 2024 04:01:51 GMT",
      "expires": "Thu, 17 Jul 2025 22:08:54 GMT",
      "age": "",
      "server": "AkamaiNetStorage"
    },
    {
      "url": "https://ot.www.cloudflare.com/public/vendor/onetrust/scripttemplates/202503.1.0/otBannerSdk.js",
      "resource_type": "script",
      "method": "GET",
      "size": 491854,
      "status": 200,
      "content_type": "application/javascript",
      "cache_control": "public, max-age=0, must-revalidate",
      "cdn": "Cloudflare",
      "supports_http3": true,
      "etag": "W/\"93cf1315fbd8c5de8595045b97298a4d\"",
      "last_modified": "",
      "expires": "",
      "age": "",
      "server": "cloudflare"
    },
    {
      "url": "https://www.googletagmanager.com/gtag/js?id=G-8BK794H3J9&l=dataLayer&cx=c&gtm=45He5471h1v890325950za200&tag_exp=102509683~102525910~102788824~102803279~102813109~102887799~102926062~102975949~103016951~103021830~103027016~103047562~103051953",
      "resource_type": "script",
      "method": "GET",
      "size": 315094,
      "status": 200,
      "content_type": "application/javascript; charset=UTF-8",
      "cache_control": "private, max-age=900",
      "cdn": "Unknown",
      "supports_http3": true,
      "etag": "",
      "last_modified": "",
      "expires": "Tue, 08 Apr 2025 22:08:54 GMT",
      "age": "",
      "server": "Google Tag Manager"
    },
    {
      "url": "https://www.googletagmanager.com/gtag/destination?id=DC-9309168&l=dataLayer&cx=c&gtm=45je5471h1v891134139za200zb890325950&tag_exp=102509683~102788824~102803279~102813109~102887799~102926062~102975949~103016951~103021830~103027016~103047562~103051953",
      "resource_type": "script",
      "method": "GET",
      "size": 283752,
      "status": 200,
      "content_type": "application/javascript; charset=UTF-8",
      "cache_control": "private, max-age=900",
      "cdn": "Unknown",
      "supports_http3": true,
      "etag": "",
      "last_modified": "Tue, 08 Apr 2025 21:27:00 GMT",
      "expires": "Tue, 08 Apr 2025 22:08:55 GMT",
      "age": "",
      "server": "Google Tag Manager"
    }
  ],
  "stylesheets": [
    {
      "url": "https://blog.cloudflare.com/themes/ashes.min.css",
      "resource_type": "stylesheet",
      "method": "GET",
      "size": 1461,
      "status": 200,
      "content_type": "text/css; charset=utf-8",
      "cache_control": "public, max-age=1200",
      "cdn": "Cloudflare",
      "supports_http3": true,
      "etag": "W/\"1262939bc96fc54a220d457b3b2113bc\"",
      "last_modified": "",
      "expires": "Tue, 08 Apr 2025 22:28:54 GMT",
      "age": "",
      "server": "cloudflare"
    },
    {
      "url": "https://blog.cloudflare.com/_astro/index.Bpd2cWaZ.css",
      "resource_type": "stylesheet",
      "method": "GET",
      "size": 99696,
      "status": 200,
      "content_type": "text/css; charset=utf-8",
      "cache_control": "public, max-age=1200",
      "cdn": "Cloudflare",
      "supports_http3": true,
      "etag": "W/\"bd42c304c46bdd7915f63edf9cb29f5d\"",
      "last_modified": "",
      "expires": "Tue, 08 Apr 2025 22:28:54 GMT",
      "age": "4221",
      "server": "cloudflare"
    }
  ],
  "fonts": [],
  "api_responses": [
    {
      "url": "https://ot.www.cloudflare.com/public/vendor/onetrust/consent/b1e05d49-f072-4bae-9116-bdb78af15448/b1e05d49-f072-4bae-9116-bdb78af15448.json",
      "resource_type": "xhr",
      "method": "GET",
      "size": 5624,
      "status": 200,
      "content_type": "application/json",
      "cache_control": "public, max-age=0, must-revalidate",
      "cdn": "Cloudflare",
      "supports_http3": true,
      "etag": "W/\"6d724070b5a0492ab4fd71d2d2e4d85e\"",
      "last_modified": "",
      "expires": "",
      "age": "",
      "server": "cloudflare"
    },
    {
      "url": "https://stats.g.doubleclick.net/g/collect?t=dc&aip=1&_r=3&v=1&_v=j86&tid=G-PGV1K2BN4M&cid=1e25258f-43f8-4680-8e17-c3fdacbf762f&_u=KGDAAEADQAAAAC%7E&z=1039221210",
      "resource_type": "xhr",
      "method": "POST",
      "size": 0,
      "status": 204,
      "content_type": "text/plain",
      "cache_control": "no-cache, no-store, must-revalidate",
      "cdn": "Unknown",
      "supports_http3": true,
      "etag": "",
      "last_modified": "",
      "expires": "Fri, 01 Jan 1990 00:00:00 GMT",
      "age": "",
      "server": "Golfe2"
    },
    {
      "url": "https://www.google.com/ads/ga-audiences?t=sr&aip=1&_r=4&v=1&_v=j86&tid=G-PGV1K2BN4M&cid=1e25258f-43f8-4680-8e17-c3fdacbf762f&_u=KGDAAEADQAAAAC%7E&z=1039221210&slf_rd=1",
      "resource_type": "fetch",
      "method": "GET",
      "size": 0
    },
    {
      "url": "https://geolocation.onetrust.com/cookieconsentpub/v1/geo/location",
      "resource_type": "xhr",
      "method": "GET",
      "size": 59,
      "status": 200,
      "content_type": "application/json",
      "cache_control": "",
      "cdn": "Cloudflare",
      "etag": "",
      "last_modified": "",
      "expires": "",
      "age": "",
      "server": "cloudflare"
    },
    {
      "url": "https://blog.cloudflare.com/static/z/t",
      "resource_type": "fetch",
      "method": "POST",
      "size": 239,
      "status": 200,
      "content_type": "application/json",
      "cache_control": "",
      "cdn": "Cloudflare",
      "supports_http3": true,
      "etag": "",
      "last_modified": "",
      "expires": "",
      "age": "",
      "server": "cloudflare"
    },
    {
      "url": "https://px.ads.linkedin.com/attribution_trigger?pid=28851&time=1744150134707&url=https%3A%2F%2Fblog.cloudflare.com%2F",
      "resource_type": "xhr",
      "method": "GET",
      "size": 2,
      "status": 200,
      "content_type": "application/json",
      "cache_control": "",
      "cdn": "Unknown",
      "etag": "",
      "last_modified": "",
      "expires": "",
      "age": "",
      "server": ""
    },
    {
      "url": "https://blog.cloudflare.com/static/z/t",
      "resource_type": "fetch",
      "method": "POST",
      "size": 0
    },
    {
      "url": "https://blog.cloudflare.com/static/z/t",
      "resource_type": "fetch",
      "method": "POST",
      "size": 0
    },
    {
      "url": "https://scout.salesloft.com/r?tid=eyJ0eXAiOiJKV1QiLCJhbGciOiJIUzI1NiJ9.eyJ0IjoxMDkyNjh9.dguW7jthV1Y1wgRcAJfVrR_xsANK7zX9ZiD1wf0suvY",
      "resource_type": "xhr",
      "method": "GET",
      "size": 41,
      "status": 200,
      "content_type": "application/json; charset=utf-8",
      "cache_control": "max-age=0, private, must-revalidate",
      "cdn": "Unknown",
      "etag": "",
      "last_modified": "",
      "expires": "",
      "age": "",
      "server": ""
    },
    {
      "url": "https://scout.salesloft.com/i",
      "resource_type": "xhr",
      "method": "GET",
      "size": 48,
      "status": 200,
      "content_type": "application/json; charset=utf-8",
      "cache_control": "max-age=0, private, must-revalidate",
      "cdn": "Unknown",
      "etag": "",
      "last_modified": "",
      "expires": "",
      "age": "",
      "server": ""
    },
    {
      "url": "https://ot.www.cloudflare.com/public/vendor/onetrust/consent/b1e05d49-f072-4bae-9116-bdb78af15448/018debfb-4917-76f1-8862-8a2f83812baa/en.json",
      "resource_type": "fetch",
      "method": "GET",
      "size": 86481,
      "status": 200,
      "content_type": "application/json",
      "cache_control": "public, max-age=0, must-revalidate",
      "cdn": "Cloudflare",
      "supports_http3": true,
      "etag": "W/\"d6dcc001a66be1afb9b11af3e565a9b8\"",
      "last_modified": "",
      "expires": "",
      "age": "",
      "server": "cloudflare"
    },
    {
      "url": "https://blog.cloudflare.com/static/z/t",
      "resource_type": "fetch",
      "method": "POST",
      "size": 0
    },
    {
      "url": "https://blog.cloudflare.com/static/z/t",
      "resource_type": "fetch",
      "method": "POST",
      "size": 0
    },
    {
      "url": "https://blog.cloudflare.com/static/z/t",
      "resource_type": "fetch",
      "method": "POST",
      "size": 0
    },
    {
      "url": "https://ot.www.cloudflare.com/public/vendor/onetrust/scripttemplates/202503.1.0/assets/otCommonStyles.css",
      "resource_type": "fetch",
      "method": "GET",
      "size": 25157,
      "status": 200,
      "content_type": "text/css",
      "cache_control": "public, max-age=0, must-revalidate",
      "cdn": "Cloudflare",
      "supports_http3": true,
      "etag": "W/\"6a0c454f577ec8e498d377a573a8127a\"",
      "last_modified": "",
      "expires": "",
      "age": "",
      "server": "cloudflare"
    },
    {
      "url": "https://www.google-analytics.com/g/collect?v=2&tid=G-8BK794H3J9&gtm=45je5471h1v891134139z8890325950za200zb890325950&_p=1744150134602&gcs=G111&gcd=13r3r3r3r5l1&npa=0&dma=0&tag_exp=102509683~102788824~102803279~102813109~102887799~102926062~102975949~103016951~103021830~103027016~103047562~103051953&ul=en-US%40posix&cid=700726147.1744150135&sr=1280x800&uaa=x64&uab=64&uafvl=Chromium%3B134.0.6998.35%7CNot%253AA-Brand%3B24.0.0.0%7CHeadlessChrome%3B134.0.6998.35&uamb=0&uam=&uap=Windows&uapv=10.0&uaw=0&are=1&frm=0&pscdl=noapi&_s=1&dt=The%20Cloudflare%20Blog&sid=1744150135&sct=1&seg=0&dl=https%3A%2F%2Fblog.cloudflare.com%2F&_tu=SA&en=page_view&_fv=1&_nsi=1&_ss=1&ep.gtm_container_id=GTM-NDGPDFZ&ep.gtm_container_version=68&ep.user_agent_string=Mozilla%2F5.0%20(Windows%20NT%2010.0%3B%20Win64%3B%20x64)%20AppleWebKit%2F537.36%20(KHTML%2C%20like%20Gecko)%20Chrome%2F94.0.4606.81%20Safari%2F537.36&ep.external_referrer=&ep.site=blog&ep.previous_url=&ep.logged_in=false&ep.locale=en-us&ep.demandbase_audience=%7BNon-Company%20Visitor%7D&ep.demandbase_city=%7BNon-Company%20Visitor%7D&ep.demandbase_company_sid=%7BNon-Company%20Visitor%7D&ep.demandbase_company_name=%7BNon-Company%20Visitor%7D&ep.demandbase_country_name=%7BNon-Company%20Visitor%7D&ep.demandbase_employee_range=%7BNon-Company%20Visitor%7D&ep.demandbase_industry=%7BNon-Company%20Visitor%7D&ep.demandbase_marketing_alias=%7BNon-Company%20Visitor%7D&ep.demandbase_revenue_range=%7BNon-Company%20Visitor%7D&ep.demandbase_state=%7BNon-Company%20Visitor%7D&ep.demandbase_sub_industry=%7BNon-Company%20Visitor%7D&ep.demandbase_web_site=%7BNon-Company%20Visitor%7D&ep.gtm_tag_name=GA4%20-%20Page%20View&ep.page_url=https%3A%2F%2Fblog.cloudflare.com%2F&up.client_id_string=s&up.logged_in=false&up.language=en-US%40posix&up.locale=en-us&tfd=1443",
      "resource_type": "fetch",
      "method": "POST",
      "size": 0
    },
    {
      "url": "https://px.ads.linkedin.com/wa/",
      "resource_type": "xhr",
      "method": "POST",
      "size": 0,
      "status": 204,
      "content_type": "",
      "cache_control": "",
      "cdn": "Unknown",
      "etag": "",
      "last_modified": "",
      "expires": "",
      "age": "",
      "server": ""
    },
    {
      "url": "https://blog.cloudflare.com/cdn-cgi/rum?",
      "resource_type": "xhr",
      "method": "POST",
      "size": 0,
      "status": 204,
      "content_type": "",
      "cache_control": "",
      "cdn": "Cloudflare",
      "etag": "",
      "last_modified": "",
      "expires": "",
      "age": "",
      "server": "cloudflare"
    },
    {
      "url": "https://valid.rpki.cloudflare.com/?r=71028594",
      "resource_type": "fetch",
      "method": "GET",
      "size": 58,
      "status": 200,
      "content_type": "application/json",
      "cache_control": "",
      "cdn": "Cloudflare",
      "etag": "",
      "last_modified": "",
      "expires": "",
      "age": "",
      "server": "cloudflare"
    },
    {
      "url": "https://invalid.rpki.cloudflare.com/?r=69979281",
      "resource_type": "fetch",
      "method": "GET",
      "size": 58,
      "status": 200,
      "content_type": "application/json",
      "cache_control": "",
      "cdn": "Cloudflare",
      "etag": "",
      "last_modified": "",
      "expires": "",
      "age": "",
      "server": "cloudflare"
    },
    {
      "url": "https://performance.radar.cloudflare.com/api/beacon",
      "resource_type": "fetch",
      "method": "POST",
      "size": 15,
      "status": 200,
      "content_type": "application/json;charset=UTF-8",
      "cache_control": "",
      "cdn": "Cloudflare",
      "supports_http3": true,
      "etag": "",
      "last_modified": "",
      "expires": "",
      "age": "",
      "server": "cloudflare"
    }
  ],
  "html": [
    {
      "url": "https://blog.cloudflare.com/",
      "resource_type": "document",
      "method": "GET",
      "size": 97680,
      "status": 200,
      "content_type": "text/html",
      "cache_control": "",
      "cdn": "Cloudflare",
      "supports_http3": true,
      "etag": "",
      "last_modified": "",
      "expires": "",
      "age": "",
      "server": "cloudflare"
    },
    {
      "url": "https://www.googletagmanager.com/static/service_worker/5430/sw_iframe.html?origin=https%3A%2F%2Fblog.cloudflare.com",
      "resource_type": "document",
      "method": "GET",
      "size": 3537,
      "status": 200,
      "content_type": "text/html",
      "cache_control": "public, max-age=31536000",
      "cdn": "Unknown",
      "supports_http3": true,
      "etag": "",
      "last_modified": "Thu, 03 Apr 2025 09:18:00 GMT",
      "expires": "Fri, 03 Apr 2026 16:02:58 GMT",
      "age": "453956",
      "server": "sffe"
    },
    {
      "url": "https://td.doubleclick.net/td/fls/rul/activityi;fledge=1;src=9309168;type=a_pag0;cat=3_page;ord=3672008124660;npa=0;auiddc=1685469183.1744150135;u1=page_load;u2=undefined;u3=%2F;u4=en-us;u5=undefined;u6=undefined;u7=undefined;u8=undefined;u9=undefined;u10=undefined;u12=undefined;ps=1;pcor=252796916;uaa=x64;uab=64;uafvl=Chromium%3B134.0.6998.35%7CNot%253AA-Brand%3B24.0.0.0%7CHeadlessChrome%3B134.0.6998.35;uamb=0;uam=;uap=Windows;uapv=10.0;uaw=0;pscdl=noapi;frm=0;_tu=KlA;gtm=45fe5471h1v9164255219z8890325950za201zb891134139;gcs=G111;gcd=13r3r3r3r5l1;dma=0;dc_fmt=9;tag_exp=102509682~102788824~102803279~102813109~102887800~102926062~102975949~103016951~103021830~103027016~103047562~103051953;epver=2?",
      "resource_type": "document",
      "method": "GET",
      "size": 13,
      "status": 200,
      "content_type": "text/html; charset=UTF-8",
      "cache_control": "no-cache, must-revalidate",
      "cdn": "Unknown",
      "supports_http3": true,
      "etag": "",
      "last_modified": "",
      "expires": "Fri, 01 Jan 1990 00:00:00 GMT",
      "age": "",
      "server": "cafe"
    }
  ],
  "other": [
    {
      "url": "https://713-xsc-918.mktoresp.com/webevents/visitWebPage?_mchNc=1744150134727&_mchCn=&_mchId=713-XSC-918&_mchTk=_mch-cloudflare.com-7d5ec7b05639cc216b2bca972dee5b56&_mchHo=blog.cloudflare.com&_mchPo=&_mchRu=%2F&_mchPc=https%3A&_mchVr=164&_mchEcid=&_mchHa=&_mchRe=&_mchQp=",
      "resource_type": "ping",
      "method": "POST",
      "size": 2,
      "status": 200,
      "content_type": "text/plain; charset=UTF-8",
      "cache_control": "",
      "cdn": "Unknown",
      "etag": "",
      "last_modified": "",
      "expires": "",
      "age": "",
      "server": "nginx/1.20.1"
    },
    {
      "url": "https://www.google.com/ccm/collect?en=page_view&dl=https%3A%2F%2Fblog.cloudflare.com%2F&scrsrc=www.googletagmanager.com&frm=0&rnd=947391129.1744150135&dt=The%20Cloudflare%20Blog&auid=1685469183.1744150135&navt=n&npa=0&_tu=CA&gtm=45He5471h1v890325950za200&gcs=G111&gcd=13r3r3r3r5l1&dma=0&tag_exp=102509683~102525910~102788824~102803279~102813109~102887799~102926062~102975949~103016951~103021830~103027016~103047562~103051953&tft=1744150134912&tfd=1282&apve=1",
      "resource_type": "ping",
      "method": "POST",
      "size": 0,
      "status": 200,
      "content_type": "",
      "cache_control": "",
      "cdn": "Unknown",
      "etag": "",
      "last_modified": "",
      "expires": "",
      "age": "",
      "server": ""
    }
  ]
}